hvi_wrap/__init__.py
hvi_wrap/_fpga_register.py
hvi_wrap/_hvi_register.py
hvi_wrap/_runtime.py
hvi_wrap/_sync_block.py
hvi_wrap/_triggers.py
hvi_wrap/_utils.py
hvi_wrap/Hvi.py
hvi_wrap/ModuleDescriptor.py
hvi_wrap-1.1.1.dist-info/METADATA
hvi_wrap-1.1.1.dist-info/WHEEL
hvi_wrap-1.1.1.dist-info/RECORD
